proxy_decorator/__init__.py
proxy_decorator/proxy_decorator.py
proxy_decorator-0.1.2.dist-info/METADATA
proxy_decorator-0.1.2.dist-info/WHEEL
proxy_decorator-0.1.2.dist-info/top_level.txt
proxy_decorator-0.1.2.dist-info/RECORD
