Metadata-Version: 2.1
Name: proxy-decorator
Version: 0.1.2
Summary: A simple proxy decorator for Python functions
Author-email: joe_zhouman <man.man.man.man.a@gmail.com>
Classifier: Programming Language :: Python :: 3
Classifier: License :: OSI Approved :: MIT License
Classifier: Operating System :: OS Independent
Classifier: Development Status :: 3 - Alpha
Requires-Python: >=3.7
